events_protocol/__init__.py
events_protocol/client/__init__.py
events_protocol/client/event_client.py
events_protocol/client/http.py
events_protocol/client/exception/__init__.py
events_protocol/client/exception/request_exception.py
events_protocol/core/__init__.py
events_protocol/core/builder.py
events_protocol/core/context.py
events_protocol/core/exception.py
events_protocol/core/logging/__init__.py
events_protocol/core/logging/supressor.py
events_protocol/core/logging/mixins/__init__.py
events_protocol/core/logging/mixins/loggable.py
events_protocol/core/model/__init__.py
events_protocol/core/model/base.py
events_protocol/core/model/event.py
events_protocol/core/model/event_type.py
events_protocol/core/model/payload.py
events_protocol/core/model/user.py
events_protocol/core/utils/__init__.py
events_protocol/core/utils/sync.py
events_protocol/server/__init__.py
events_protocol/server/handler/__init__.py
events_protocol/server/handler/event_handler.py
events_protocol/server/handler/event_handler_discovery.py
events_protocol/server/handler/event_handler_registry.py
events_protocol/server/parser/__init__.py
events_protocol/server/parser/event_processor.py
tests/__init__.py
tests/client/__init__.py
tests/client/test_event_client.py
tests/client/test_http.py
tests/core/__init__.py
tests/core/test_context.py
tests/server/__init__.py
tests/server/handler/__init__.py
tests/server/handler/test_event_handler_discovery.py
tests/server/handler/test_event_handler_registry.py
tests/server/parser/__init__.py
tests/server/parser/test_event_processor.py
events_protocol-0.2.4.dist-info/LICENSE
events_protocol-0.2.4.dist-info/METADATA
events_protocol-0.2.4.dist-info/WHEEL
events_protocol-0.2.4.dist-info/top_level.txt
events_protocol-0.2.4.dist-info/RECORD
