Metadata-Version: 2.1
Name: events-protocol
Version: 0.2.4
Summary: Library to be a Client and Server using event protocol
Home-page: https://github.com/GuiaBolso/events-protocol-python
Author: Guiabolso
License: Apache-2.0
Project-URL: Documentation, https://events-protocol.readthedocs.io/en/stable/
Project-URL: Source Code, https://github.com/GuiaBolso/events-protocol-python
Platform: UNKNOWN
Classifier: Intended Audience :: Developers
Classifier: License :: OSI Approved :: Apache Software License
Classifier: Operating System :: Unix
Classifier: Operating System :: POSIX :: Linux
Classifier: Operating System :: MacOS
Classifier: Programming Language :: Python :: 3.7
Classifier: Programming Language :: Python :: 3.8
Classifier: Programming Language :: Python :: 3 :: Only
Classifier: Topic :: Software Development :: Libraries :: Python Modules
Requires-Python: >=3.7
License-File: LICENSE
Requires-Dist: certifi (>=2019.11.28)
Requires-Dist: chardet (>=3.0.4)
Requires-Dist: idna (>=2.8)
Requires-Dist: pydantic (>=1.4)
Requires-Dist: requests (>=2.22.0)
Requires-Dist: urllib3 (>=1.25.8)
Provides-Extra: doc
Requires-Dist: Sphinx (==2.4.1) ; extra == 'doc'
Requires-Dist: sphinx-autoapi (==1.2.1) ; extra == 'doc'
